TNet_Seg/__init__.py
TNet_Seg/loss.py
TNet_Seg/net.py
TNet_Seg/visualize.py
tnet_seg-0.1.0.dist-info/METADATA
tnet_seg-0.1.0.dist-info/WHEEL
tnet_seg-0.1.0.dist-info/RECORD
