Metadata-Version: 2.1
Name: TNet-Seg
Version: 0.1.0
Summary: pytorch module for T-Net image segmentation model with DiceLoss and code for visualization of model
Author: Harish-Natarajan
Author-email: harishnatarajan24@gmail.com
Requires-Python: >=3.8,<4.0
Classifier: Programming Language :: Python :: 3
Classifier: Programming Language :: Python :: 3.8
Classifier: Programming Language :: Python :: 3.9
Classifier: Programming Language :: Python :: 3.10
Classifier: Programming Language :: Python :: 3.11
Classifier: Programming Language :: Python :: 3.12
Requires-Dist: torch (==2.1.1)
Requires-Dist: torchinfo (==1.8.0)
